{
    "id": "audiopids-lib",
    "version": "11.0.0",
    "compatibility": {
        "minimum": "11",
        "verified": "11",
        "maximum": "11"
    },
    "title": "Audio PIDs Lib",
    "description": "A library to help you to work with audio PIDs.",
    "languages": [
        {
            "lang": "en",
            "name": "English",
            "path": "lang/en.json"
        }
    ],
    "url": "https://github.com/patrickporto/audiopids-lib",
    "library": true,
    "esmodules": [
        "audiopids-lib.js"
    ]
}
